btcpy/__init__.py
btcpy/constants.py
btcpy/setup.py
btcpy/lib/__init__.py
btcpy/lib/base58.py
btcpy/lib/bech32.py
btcpy/lib/codecs.py
btcpy/lib/opcodes.py
btcpy/lib/parsing.py
btcpy/lib/types.py
btcpy/structs/__init__.py
btcpy/structs/address.py
btcpy/structs/block.py
btcpy/structs/crypto.py
btcpy/structs/hd.py
btcpy/structs/script.py
btcpy/structs/sig.py
btcpy/structs/transaction.py
tests/__init__.py
tests/integration.py
tests/regtest.py
tests/unit.py
chainside_btcpy-0.6.5.dist-info/LICENSE
chainside_btcpy-0.6.5.dist-info/METADATA
chainside_btcpy-0.6.5.dist-info/WHEEL
chainside_btcpy-0.6.5.dist-info/top_level.txt
chainside_btcpy-0.6.5.dist-info/RECORD
